sdh/forms/__init__.py
sdh/forms/base.py
sdh/forms/conf.py
sdh/forms/fields.py
sdh/forms/forms.py
sdh/forms/formsets.py
sdh/forms/formsets.py.orig
sdh/forms/renderers.py
sdh/forms/widgets.py
sdh/forms/templates/sdh/forms/field.html
sdh/forms/templates/sdh/forms/form.html
sdh/forms/templates/sdh/forms/widgets/label_input.html
sdh/forms/templates/sdh/forms/widgets/multiple_label_input.html
sdh/forms/templatetags/__init__.py
sdh/forms/templatetags/sdhforms.py
sdh_forms-2.4.2.dist-info/LICENSE
sdh_forms-2.4.2.dist-info/METADATA
sdh_forms-2.4.2.dist-info/WHEEL
sdh_forms-2.4.2.dist-info/top_level.txt
sdh_forms-2.4.2.dist-info/RECORD
