Metadata-Version: 2.1
Name: sdh.forms
Version: 2.4.2
Summary: sdh.forms library wrap Django forms with custom template-way render solution.
Author-email: Viacheslav Vic Bukhantsov <vic.bukhantsov@gmail.com>, Borys Vorona <borysvorona@gmail.com>, Alexey Babarykin <mobil.light@gmail.com>, Oleg Kozij <olekhelk@gmail.com>
Maintainer-email: Viacheslav Vic Bukhantsov <vic.bukhantsov@gmail.com>
License: Copyright (c) 2025, SDH-IT GmbH
Project-URL: Repository, https://github.com/sdh-global/sdh-forms
Classifier: Development Status :: 5 - Production/Stable
Classifier: Intended Audience :: Developers
Classifier: Framework :: Django
Classifier: License :: OSI Approved :: BSD License
Classifier: Operating System :: OS Independent
Classifier: Programming Language :: Python
Classifier: Programming Language :: Python :: 3
Classifier: Programming Language :: Python :: 3.8
Classifier: Programming Language :: Python :: 3.9
Classifier: Topic :: Internet :: WWW/HTTP :: Dynamic Content
Classifier: Topic :: Software Development
Classifier: Topic :: Software Development :: Libraries
Requires-Python: >=3.8
License-File: LICENSE
Requires-Dist: Django >=3.2
